modespy/__init__.py
modespy/filters.py
modespy/methods.py
modespy/modes.py
modespy/std_problems.py
modespy/tk_examples.py
modespy/util.py
modespy-0.9.0.dist-info/LICENSE
modespy-0.9.0.dist-info/METADATA
modespy-0.9.0.dist-info/WHEEL
modespy-0.9.0.dist-info/top_level.txt
modespy-0.9.0.dist-info/RECORD
