Metadata-Version: 2.1
Name: modespy
Version: 0.9.0
Summary: Parameterised linear multi-step methods for the solution of Ordinary Differential Equations (ODEs).
Home-page: https://github.com/ericjwhitney/modespy
Author: Eric J. Whitney
Author-email: eric.j.whitney1@optusnet.removethispart.com.au
License: UNKNOWN
Keywords: ODE differential equations mathematics
Platform: UNKNOWN
Classifier: Development Status :: 3 - Alpha
Classifier: Intended Audience :: Science/Research
Classifier: License :: OSI Approved :: MIT License
Classifier: Natural Language :: English
Classifier: Operating System :: OS Independent
Classifier: Programming Language :: Python :: 3.7
Classifier: Topic :: Scientific/Engineering :: Mathematics
Requires-Python: >=3.7
Requires-Dist: numpy
Requires-Dist: scipy
